jaspion/__init__.py
jaspion/abc.py
jaspion/app.py
jaspion/cli.py
jaspion/sketch.py
jaspion/utils.py
Jaspion-0.3.5.dist-info/LICENSE
Jaspion-0.3.5.dist-info/METADATA
Jaspion-0.3.5.dist-info/WHEEL
Jaspion-0.3.5.dist-info/entry_points.txt
Jaspion-0.3.5.dist-info/top_level.txt
Jaspion-0.3.5.dist-info/RECORD
