Metadata-Version: 2.1
Name: Jaspion
Version: 0.3.5
Summary: FreeSwitch Event Handler based in Flask.
Home-page: https://github.com/Otoru/Jaspion
Author: Vitor Hugo de Oliveira Vargas
Author-email: vitor.hugo@sippulse.com
License: MIT
Project-URL: Bug Reports, https://github.com/Otoru/Jaspion/issues
Project-URL: Source Code, https://github.com/Otoru/Jaspion
Project-URL: Docs, https://github.com/Otoru/jaspion/wiki
Keywords: ESL,FreeSwitch
Platform: UNKNOWN
Classifier: Development Status :: 4 - Beta
Classifier: License :: OSI Approved :: MIT License
Classifier: Intended Audience :: Information Technology
Classifier: Intended Audience :: Telecommunications Industry
Classifier: Natural Language :: Portuguese (Brazilian)
Classifier: Operating System :: Unix
Classifier: Programming Language :: Python :: 3.6
Classifier: Programming Language :: Python :: 3.7
Classifier: Topic :: Communications :: Telephony
Classifier: Topic :: Software Development
Classifier: Topic :: Software Development :: Libraries :: Application Frameworks
Classifier: Topic :: Software Development :: Libraries :: Python Modules
Requires-Dist: greenswitch
Provides-Extra: dev
Requires-Dist: ipython ; extra == 'dev'
Requires-Dist: pylint ; extra == 'dev'
